{
 "cells": [
  {
   "cell_type": "markdown",
   "metadata": {},
   "source": [
    "## 03 Lists vs Tuples"
   ]
  },
  {
   "cell_type": "code",
   "execution_count": 1,
   "metadata": {},
   "outputs": [
    {
     "name": "stdout",
     "output_type": "stream",
     "text": [
      "  1           0 LOAD_CONST               0 ((1, 2, 3, 4))\n",
      "              2 RETURN_VALUE\n"
     ]
    }
   ],
   "source": [
    "from dis import dis\n",
    "dis(compile('(1,2,3,4)', 'string', 'eval'))"
   ]
  },
  {
   "cell_type": "code",
   "execution_count": 7,
   "metadata": {},
   "outputs": [
    {
     "name": "stdout",
     "output_type": "stream",
     "text": [
      "  1           0 BUILD_LIST               0\n",
      "              2 LOAD_CONST               0 ((1, 2, 3, 4, 'a'))\n",
      "              4 LIST_EXTEND              1\n",
      "              6 RETURN_VALUE\n"
     ]
    }
   ],
   "source": [
    "dis(compile('[1,2,3,4, \"a\"]', 'string', 'eval'))"
   ]
  },
  {
   "cell_type": "code",
   "execution_count": 8,
   "metadata": {},
   "outputs": [
    {
     "name": "stdout",
     "output_type": "stream",
     "text": [
      "  1           0 LOAD_CONST               0 (1)\n",
      "              2 LOAD_CONST               1 (2)\n",
      "              4 LOAD_CONST               2 (3)\n",
      "              6 LOAD_CONST               3 (4)\n",
      "              8 LOAD_CONST               4 ('a')\n",
      "             10 LOAD_NAME                0 (q)\n",
      "             12 LOAD_NAME                1 (w)\n",
      "             14 BUILD_LIST               2\n",
      "             16 BUILD_LIST               6\n",
      "             18 RETURN_VALUE\n"
     ]
    }
   ],
   "source": [
    "dis(compile('[1,2,3,4, \"a\", [q,w]]', 'string', 'eval'))"
   ]
  },
  {
   "cell_type": "code",
   "execution_count": 10,
   "metadata": {},
   "outputs": [
    {
     "data": {
      "text/plain": [
       "0.00025410000125702936"
      ]
     },
     "execution_count": 10,
     "metadata": {},
     "output_type": "execute_result"
    }
   ],
   "source": [
    "from timeit import timeit\n",
    "timeit('(1,2,3,4)', number=10000)"
   ]
  },
  {
   "cell_type": "code",
   "execution_count": 12,
   "metadata": {},
   "outputs": [
    {
     "data": {
      "text/plain": [
       "0.0009171999990940094"
      ]
     },
     "execution_count": 12,
     "metadata": {},
     "output_type": "execute_result"
    }
   ],
   "source": [
    "from timeit import timeit\n",
    "timeit('[1,2,3,4]', number=10000)"
   ]
  },
  {
   "cell_type": "code",
   "execution_count": 13,
   "metadata": {},
   "outputs": [],
   "source": [
    "# Copying Sequences\n"
   ]
  },
  {
   "cell_type": "code",
   "execution_count": 16,
   "metadata": {},
   "outputs": [
    {
     "name": "stdout",
     "output_type": "stream",
     "text": [
      "[[10], 20, 30]\n",
      "[[1000], 20, 30]\n",
      "2470688477680 2470688477680\n"
     ]
    }
   ],
   "source": [
    "# Shallow Copy - copy the containers but not the elements inside\n",
    "s = [[10], 20, 30]\n",
    "s1 = s.copy()\n",
    "print(s1)\n",
    "s1[0][0] = 1000\n",
    "print(s)\n",
    "print(id(s1[0][0]), id(s[0][0])) # same address\n"
   ]
  },
  {
   "cell_type": "code",
   "execution_count": null,
   "metadata": {},
   "outputs": [],
   "source": []
  },
  {
   "cell_type": "code",
   "execution_count": null,
   "metadata": {},
   "outputs": [],
   "source": []
  }
 ],
 "metadata": {
  "interpreter": {
   "hash": "578aa1710721ebb0cd4e3b8e419f7437728ee3837e632204dd7a023c7bca9a56"
  },
  "kernelspec": {
   "display_name": "Python 3.10.0 64-bit",
   "language": "python",
   "name": "python3"
  },
  "language_info": {
   "codemirror_mode": {
    "name": "ipython",
    "version": 3
   },
   "file_extension": ".py",
   "mimetype": "text/x-python",
   "name": "python",
   "nbconvert_exporter": "python",
   "pygments_lexer": "ipython3",
   "version": "3.10.0"
  },
  "orig_nbformat": 4
 },
 "nbformat": 4,
 "nbformat_minor": 2
}
